osw/__init__.py
osw/auth.py
osw/core.py
osw/custom_types.py
osw/defaults.py
osw/express.py
osw/ontology.py
osw/params.py
osw/sparql_client_smw.py
osw/wiki_tools.py
osw/wtsite.py
osw/controller/__init__.py
osw/controller/database.py
osw/controller/entity.py
osw/controller/page_package.py
osw/controller/file/__init__.py
osw/controller/file/base.py
osw/controller/file/local.py
osw/controller/file/memory.py
osw/controller/file/remote.py
osw/controller/file/s3.py
osw/controller/file/wiki.py
osw/data/__init__.py
osw/data/import_utility.py
osw/data/mining.py
osw/model/__init__.py
osw/model/entity.py
osw/model/page_package.py
osw/model/static.py
osw/utils/__init__.py
osw/utils/oold.py
osw/utils/regex.py
osw/utils/regex_pattern.py
osw/utils/strings.py
osw/utils/templates.py
osw/utils/util.py
osw/utils/wiki.py
osw/utils/wikitext.py
osw/utils/workflow.py
osw-0.35.0.dist-info/licenses/LICENSE.txt
osw-0.35.0.dist-info/METADATA
osw-0.35.0.dist-info/WHEEL
osw-0.35.0.dist-info/top_level.txt
osw-0.35.0.dist-info/RECORD
