Metadata-Version: 2.4
Name: osw
Version: 0.35.0
Summary: Python toolset for data processing, queries, wikicode generation and page manipulation
Home-page: https://github.com/OpenSemanticLab/osw-python
Author: "Simon Stier"
Author-email: simon.stier@isc.fraunhofer.de
License: AGPL-3.0-or-later
Project-URL: Documentation, https://opensemanticlab.github.io/osw-python/
Project-URL: Source, https://github.com/OpenSemanticLab/osw-python
Project-URL: Changelog, https://github.com/OpenSemanticLab/osw-python/blob/main/CHANGELOG.md
Project-URL: Download, https://pypi.org/project/osw/#files
Platform: any
Classifier: Development Status :: 3 - Alpha
Classifier: Programming Language :: Python
Requires-Python: >=3.9
License-File: LICENSE.txt
Requires-Dist: pydantic>=1.10.17
Requires-Dist: datamodel-code-generator>=0.25
Requires-Dist: mwclient>=0.11.0
Requires-Dist: rdflib
Requires-Dist: PyLD
Requires-Dist: SPARQLWrapper
Requires-Dist: jsonpath-ng
Requires-Dist: numpy
Requires-Dist: pyyaml
Requires-Dist: pandas
Requires-Dist: typing_extensions
Requires-Dist: pathlib
Requires-Dist: sphinx
Requires-Dist: chardet
Requires-Dist: matplotlib
Requires-Dist: scipy
Requires-Dist: dask
Requires-Dist: asyncio
Requires-Dist: tqdm
Requires-Dist: pybars3-wheel
Requires-Dist: backports.strenum; python_version < "3.11"
Provides-Extra: wikitext
Requires-Dist: mwparserfromhell; extra == "wikitext"
Provides-Extra: db
Requires-Dist: psycopg2; extra == "db"
Requires-Dist: sqlalchemy; extra == "db"
Provides-Extra: s3
Requires-Dist: boto3; extra == "s3"
Provides-Extra: dataimport
Requires-Dist: geopy; extra == "dataimport"
Requires-Dist: deepl; extra == "dataimport"
Requires-Dist: openpyxl; extra == "dataimport"
Provides-Extra: ui
Requires-Dist: pysimplegui; extra == "ui"
Provides-Extra: workflow
Requires-Dist: prefect==2.20.0; extra == "workflow"
Provides-Extra: tutorial
Requires-Dist: geopy; extra == "tutorial"
Requires-Dist: deepl; extra == "tutorial"
Requires-Dist: openpyxl; extra == "tutorial"
Provides-Extra: all
Requires-Dist: geopy; extra == "all"
Requires-Dist: deepl; extra == "all"
Requires-Dist: openpyxl; extra == "all"
Requires-Dist: psycopg2; extra == "all"
Requires-Dist: sqlalchemy; extra == "all"
Requires-Dist: pysimplegui; extra == "all"
Requires-Dist: boto3; extra == "all"
Requires-Dist: mwparserfromhell; extra == "all"
Provides-Extra: dev
Requires-Dist: pre-commit>=3.2.0; extra == "dev"
Requires-Dist: tox; extra == "dev"
Provides-Extra: testing
Requires-Dist: pytest-asyncio; extra == "testing"
Requires-Dist: prefect; extra == "testing"
Requires-Dist: setuptools; extra == "testing"
Requires-Dist: pytest; extra == "testing"
Requires-Dist: pytest-cov; extra == "testing"
Requires-Dist: pytest-mock; extra == "testing"
Requires-Dist: geopy; extra == "testing"
Requires-Dist: deepl; extra == "testing"
Requires-Dist: sqlalchemy; extra == "testing"
Requires-Dist: psycopg2-binary; extra == "testing"
Requires-Dist: mwparserfromhell; extra == "testing"
Requires-Dist: jsondiff; extra == "testing"
Dynamic: license-file
